{"nodes": [{"id": "d_voice_ai_app_workers_dubbing_tasks_py", "label": "dubbing_tasks.py", "file_type": "code", "source_file": "app/workers/dubbing_tasks.py", "source_location": "L1"}, {"id": "d_voice_ai_app_workers_dubbing_tasks_ensure_source_video", "label": "_ensure_source_video()", "file_type": "code", "source_file": "app/workers/dubbing_tasks.py", "source_location": "L24", "_callable": true}, {"id": "d_voice_ai_app_workers_dubbing_tasks_update_step", "label": "_update_step()", "file_type": "code", "source_file": "app/workers/dubbing_tasks.py", "source_location": "L81", "_callable": true}, {"id": "d_voice_ai_app_workers_dubbing_tasks_run_dubbing_pipeline", "label": "run_dubbing_pipeline()", "file_type": "code", "source_file": "app/workers/dubbing_tasks.py", "source_location": "L94", "_callable": true}, {"id": "d_voice_ai_app_workers_dubbing_tasks_rationale_1", "label": "Dubbing Pipeline Worker - Real AI Processing Executes 20-step dubbing pipeline u", "file_type": "rationale", "source_file": "app/workers/dubbing_tasks.py", "source_location": "L1"}, {"id": "d_voice_ai_app_workers_dubbing_tasks_rationale_25", "label": "Ensure the source video file exists at source_path.     If it was deleted (e.g.", "file_type": "rationale", "source_file": "app/workers/dubbing_tasks.py", "source_location": "L25"}, {"id": "d_voice_ai_app_workers_dubbing_tasks_rationale_82", "label": "Helper to update step status and job progress", "file_type": "rationale", "source_file": "app/workers/dubbing_tasks.py", "source_location": "L82"}, {"id": "d_voice_ai_app_workers_dubbing_tasks_rationale_95", "label": "Execute the 20-step dubbing pipeline with REAL AI processing.     Downloads vide", "file_type": "rationale", "source_file": "app/workers/dubbing_tasks.py", "source_location": "L95"}, {"id": "d_voice_ai_app_workers_dubbing_tasks_rationale_429", "label": "# NOTE: We intentionally keep source_path alive until explicitly cleaned", "file_type": "rationale", "source_file": "app/workers/dubbing_tasks.py", "source_location": "L429"}], "edges": [{"source": "d_voice_ai_app_workers_dubbing_tasks_py", "target": "os", "relation": "imports", "context": "import", "confidence": "EXTRACTED", "source_file": "app/workers/dubbing_tasks.py", "source_location": "L6", "weight": 1.0}, {"source": "d_voice_ai_app_workers_dubbing_tasks_py", "target": "time", "relation": "imports", "context": "import", "confidence": "EXTRACTED", "source_file": "app/workers/dubbing_tasks.py", "source_location": "L7", "weight": 1.0}, {"source": "d_voice_ai_app_workers_dubbing_tasks_py", "target": "shutil", "relation": "imports", "context": "import", "confidence": "EXTRACTED", "source_file": "app/workers/dubbing_tasks.py", "source_location": "L8", "weight": 1.0}, {"source": "d_voice_ai_app_workers_dubbing_tasks_py", "target": "subprocess", "relation": "imports", "context": "import", "confidence": "EXTRACTED", "source_file": "app/workers/dubbing_tasks.py", "source_location": "L9", "weight": 1.0}, {"source": "d_voice_ai_app_workers_dubbing_tasks_py", "target": "json", "relation": "imports", "context": "import", "confidence": "EXTRACTED", "source_file": "app/workers/dubbing_tasks.py", "source_location": "L10", "weight": 1.0}, {"source": "d_voice_ai_app_workers_dubbing_tasks_py", "target": "logging", "relation": "imports", "context": "import", "confidence": "EXTRACTED", "source_file": "app/workers/dubbing_tasks.py", "source_location": "L11", "weight": 1.0}, {"source": "d_voice_ai_app_workers_dubbing_tasks_py", "target": "datetime", "relation": "imports_from", "context": "import", "confidence": "EXTRACTED", "source_file": "app/workers/dubbing_tasks.py", "source_location": "L12", "weight": 1.0}, {"source": "d_voice_ai_app_workers_dubbing_tasks_py", "target": "sqlalchemy_orm", "relation": "imports_from", "context": "import", "confidence": "EXTRACTED", "source_file": "app/workers/dubbing_tasks.py", "source_location": "L13", "weight": 1.0}, {"source": "d_voice_ai_app_workers_dubbing_tasks_py", "target": "app_config", "relation": "imports_from", "context": "import", "confidence": "EXTRACTED", "source_file": "app/workers/dubbing_tasks.py", "source_location": "L15", "weight": 1.0}, {"source": "d_voice_ai_app_workers_dubbing_tasks_py", "target": "app_database", "relation": "imports_from", "context": "import", "confidence": "EXTRACTED", "source_file": "app/workers/dubbing_tasks.py", "source_location": "L16", "weight": 1.0}, {"source": "d_voice_ai_app_workers_dubbing_tasks_py", "target": "app_models_job", "relation": "imports_from", "context": "import", "confidence": "EXTRACTED", "source_file": "app/workers/dubbing_tasks.py", "source_location": "L17", "weight": 1.0}, {"source": "d_voice_ai_app_workers_dubbing_tasks_py", "target": "app_services_link_adapters", "relation": "imports_from", "context": "import", "confidence": "EXTRACTED", "source_file": "app/workers/dubbing_tasks.py", "source_location": "L18", "weight": 1.0}, {"source": "d_voice_ai_app_workers_dubbing_tasks_py", "target": "app_utils_ffmpeg_utils", "relation": "imports_from", "context": "import", "confidence": "EXTRACTED", "source_file": "app/workers/dubbing_tasks.py", "source_location": "L19", "weight": 1.0}, {"source": "d_voice_ai_app_workers_dubbing_tasks_py", "target": "d_voice_ai_app_workers_dubbing_tasks_ensure_source_video", "relation": "contains", "confidence": "EXTRACTED", "source_file": "app/workers/dubbing_tasks.py", "source_location": "L24", "weight": 1.0}, {"source": "d_voice_ai_app_workers_dubbing_tasks_py", "target": "d_voice_ai_app_workers_dubbing_tasks_update_step", "relation": "contains", "confidence": "EXTRACTED", "source_file": "app/workers/dubbing_tasks.py", "source_location": "L81", "weight": 1.0}, {"source": "d_voice_ai_app_workers_dubbing_tasks_py", "target": "d_voice_ai_app_workers_dubbing_tasks_run_dubbing_pipeline", "relation": "contains", "confidence": "EXTRACTED", "source_file": "app/workers/dubbing_tasks.py", "source_location": "L94", "weight": 1.0}, {"source": "d_voice_ai_app_workers_dubbing_tasks_run_dubbing_pipeline", "target": "d_voice_ai_app_workers_dubbing_tasks_ensure_source_video", "relation": "calls", "context": "call", "confidence": "EXTRACTED", "source_file": "app/workers/dubbing_tasks.py", "source_location": "L384", "weight": 1.0}, {"source": "d_voice_ai_app_workers_dubbing_tasks_rationale_1", "target": "d_voice_ai_app_workers_dubbing_tasks_py", "relation": "rationale_for", "confidence": "EXTRACTED", "source_file": "app/workers/dubbing_tasks.py", "source_location": "L1", "weight": 1.0}, {"source": "d_voice_ai_app_workers_dubbing_tasks_rationale_25", "target": "d_voice_ai_app_workers_dubbing_tasks_ensure_source_video", "relation": "rationale_for", "confidence": "EXTRACTED", "source_file": "app/workers/dubbing_tasks.py", "source_location": "L25", "weight": 1.0}, {"source": "d_voice_ai_app_workers_dubbing_tasks_rationale_82", "target": "d_voice_ai_app_workers_dubbing_tasks_update_step", "relation": "rationale_for", "confidence": "EXTRACTED", "source_file": "app/workers/dubbing_tasks.py", "source_location": "L82", "weight": 1.0}, {"source": "d_voice_ai_app_workers_dubbing_tasks_rationale_95", "target": "d_voice_ai_app_workers_dubbing_tasks_run_dubbing_pipeline", "relation": "rationale_for", "confidence": "EXTRACTED", "source_file": "app/workers/dubbing_tasks.py", "source_location": "L95", "weight": 1.0}, {"source": "d_voice_ai_app_workers_dubbing_tasks_rationale_429", "target": "d_voice_ai_app_workers_dubbing_tasks_py", "relation": "rationale_for", "confidence": "EXTRACTED", "source_file": "app/workers/dubbing_tasks.py", "source_location": "L429", "weight": 1.0}], "raw_calls": [{"caller_nid": "d_voice_ai_app_workers_dubbing_tasks_ensure_source_video", "callee": "exists", "is_member_call": true, "source_file": "D:\\Voice_AI\\app\\workers\\dubbing_tasks.py", "source_location": "L30", "receiver": null}, {"caller_nid": "d_voice_ai_app_workers_dubbing_tasks_ensure_source_video", "callee": "warning", "is_member_call": true, "source_file": "D:\\Voice_AI\\app\\workers\\dubbing_tasks.py", "source_location": "L33", "receiver": "logger"}, {"caller_nid": "d_voice_ai_app_workers_dubbing_tasks_ensure_source_video", "callee": "get_adapter_for_url", "is_member_call": false, "source_file": "D:\\Voice_AI\\app\\workers\\dubbing_tasks.py", "source_location": "L37", "receiver": null}, {"caller_nid": "d_voice_ai_app_workers_dubbing_tasks_ensure_source_video", "callee": "FileNotFoundError", "is_member_call": false, "source_file": "D:\\Voice_AI\\app\\workers\\dubbing_tasks.py", "source_location": "L39", "receiver": null}, {"caller_nid": "d_voice_ai_app_workers_dubbing_tasks_ensure_source_video", "callee": "info", "is_member_call": true, "source_file": "D:\\Voice_AI\\app\\workers\\dubbing_tasks.py", "source_location": "L40", "receiver": "logger"}, {"caller_nid": "d_voice_ai_app_workers_dubbing_tasks_ensure_source_video", "callee": "download", "is_member_call": true, "source_file": "D:\\Voice_AI\\app\\workers\\dubbing_tasks.py", "source_location": "L41", "receiver": "adapter"}, {"caller_nid": "d_voice_ai_app_workers_dubbing_tasks_ensure_source_video", "callee": "exists", "is_member_call": true, "source_file": "D:\\Voice_AI\\app\\workers\\dubbing_tasks.py", "source_location": "L42", "receiver": null}, {"caller_nid": "d_voice_ai_app_workers_dubbing_tasks_ensure_source_video", "callee": "FileNotFoundError", "is_member_call": false, "source_file": "D:\\Voice_AI\\app\\workers\\dubbing_tasks.py", "source_location": "L43", "receiver": null}, {"caller_nid": "d_voice_ai_app_workers_dubbing_tasks_ensure_source_video", "callee": "info", "is_member_call": true, "source_file": "D:\\Voice_AI\\app\\workers\\dubbing_tasks.py", "source_location": "L44", "receiver": "logger"}, {"caller_nid": "d_voice_ai_app_workers_dubbing_tasks_ensure_source_video", "callee": "getsize", "is_member_call": true, "source_file": "D:\\Voice_AI\\app\\workers\\dubbing_tasks.py", "source_location": "L44", "receiver": null}, {"caller_nid": "d_voice_ai_app_workers_dubbing_tasks_ensure_source_video", "callee": "exists", "is_member_call": true, "source_file": "D:\\Voice_AI\\app\\workers\\dubbing_tasks.py", "source_location": "L46", "receiver": null}, {"caller_nid": "d_voice_ai_app_workers_dubbing_tasks_ensure_source_video", "callee": "copy", "is_member_call": true, "source_file": "D:\\Voice_AI\\app\\workers\\dubbing_tasks.py", "source_location": "L47", "receiver": "shutil"}, {"caller_nid": "d_voice_ai_app_workers_dubbing_tasks_ensure_source_video", "callee": "info", "is_member_call": true, "source_file": "D:\\Voice_AI\\app\\workers\\dubbing_tasks.py", "source_location": "L48", "receiver": "logger"}, {"caller_nid": "d_voice_ai_app_workers_dubbing_tasks_ensure_source_video", "callee": "FileNotFoundError", "is_member_call": false, "source_file": "D:\\Voice_AI\\app\\workers\\dubbing_tasks.py", "source_location": "L51", "receiver": null}, {"caller_nid": "d_voice_ai_app_workers_dubbing_tasks_update_step", "callee": "utcnow", "is_member_call": true, "source_file": "D:\\Voice_AI\\app\\workers\\dubbing_tasks.py", "source_location": "L90", "receiver": "datetime"}, {"caller_nid": "d_voice_ai_app_workers_dubbing_tasks_update_step", "callee": "commit", "is_member_call": true, "source_file": "D:\\Voice_AI\\app\\workers\\dubbing_tasks.py", "source_location": "L91", "receiver": "db"}, {"caller_nid": "d_voice_ai_app_workers_dubbing_tasks_run_dubbing_pipeline", "callee": "inject_ffmpeg_to_path", "is_member_call": false, "source_file": "D:\\Voice_AI\\app\\workers\\dubbing_tasks.py", "source_location": "L101", "receiver": null}, {"caller_nid": "d_voice_ai_app_workers_dubbing_tasks_run_dubbing_pipeline", "callee": "SessionLocal", "is_member_call": false, "source_file": "D:\\Voice_AI\\app\\workers\\dubbing_tasks.py", "source_location": "L103", "receiver": null}, {"caller_nid": "d_voice_ai_app_workers_dubbing_tasks_run_dubbing_pipeline", "callee": "first", "is_member_call": true, "source_file": "D:\\Voice_AI\\app\\workers\\dubbing_tasks.py", "source_location": "L105", "receiver": null}, {"caller_nid": "d_voice_ai_app_workers_dubbing_tasks_run_dubbing_pipeline", "callee": "query", "is_member_call": true, "source_file": "D:\\Voice_AI\\app\\workers\\dubbing_tasks.py", "source_location": "L105", "receiver": "db"}, {"caller_nid": "d_voice_ai_app_workers_dubbing_tasks_run_dubbing_pipeline", "callee": "DubbingJob", "is_member_call": false, "indirect": true, "context": "argument", "source_file": "D:\\Voice_AI\\app\\workers\\dubbing_tasks.py", "source_location": "L105"}, {"caller_nid": "d_voice_ai_app_workers_dubbing_tasks_run_dubbing_pipeline", "callee": "error", "is_member_call": true, "source_file": "D:\\Voice_AI\\app\\workers\\dubbing_tasks.py", "source_location": "L107", "receiver": "logger"}, {"caller_nid": "d_voice_ai_app_workers_dubbing_tasks_run_dubbing_pipeline", "callee": "info", "is_member_call": true, "source_file": "D:\\Voice_AI\\app\\workers\\dubbing_tasks.py", "source_location": "L110", "receiver": "logger"}, {"caller_nid": "d_voice_ai_app_workers_dubbing_tasks_run_dubbing_pipeline", "callee": "commit", "is_member_call": true, "source_file": "D:\\Voice_AI\\app\\workers\\dubbing_tasks.py", "source_location": "L112", "receiver": "db"}, {"caller_nid": "d_voice_ai_app_workers_dubbing_tasks_run_dubbing_pipeline", "callee": "str", "is_member_call": false, "indirect": true, "context": "argument", "source_file": "D:\\Voice_AI\\app\\workers\\dubbing_tasks.py", "source_location": "L134"}, {"caller_nid": "d_voice_ai_app_workers_dubbing_tasks_run_dubbing_pipeline", "callee": "loads", "is_member_call": true, "source_file": "D:\\Voice_AI\\app\\workers\\dubbing_tasks.py", "source_location": "L135", "receiver": "json"}, {"caller_nid": "d_voice_ai_app_workers_dubbing_tasks_run_dubbing_pipeline", "callee": "get", "is_member_call": true, "source_file": "D:\\Voice_AI\\app\\workers\\dubbing_tasks.py", "source_location": "L136", "receiver": "voice_config"}, {"caller_nid": "d_voice_ai_app_workers_dubbing_tasks_run_dubbing_pipeline", "callee": "get", "is_member_call": true, "source_file": "D:\\Voice_AI\\app\\workers\\dubbing_tasks.py", "source_location": "L137", "receiver": "voice_config"}, {"caller_nid": "d_voice_ai_app_workers_dubbing_tasks_run_dubbing_pipeline", "callee": "get", "is_member_call": true, "source_file": "D:\\Voice_AI\\app\\workers\\dubbing_tasks.py", "source_location": "L138", "receiver": "voice_config"}, {"caller_nid": "d_voice_ai_app_workers_dubbing_tasks_run_dubbing_pipeline", "callee": "select_voice", "is_member_call": false, "source_file": "D:\\Voice_AI\\app\\workers\\dubbing_tasks.py", "source_location": "L144", "receiver": null}, {"caller_nid": "d_voice_ai_app_workers_dubbing_tasks_run_dubbing_pipeline", "callee": "order_by", "is_member_call": true, "source_file": "D:\\Voice_AI\\app\\workers\\dubbing_tasks.py", "source_location": "L147", "receiver": null}, {"caller_nid": "d_voice_ai_app_workers_dubbing_tasks_run_dubbing_pipeline", "callee": "query", "is_member_call": true, "source_file": "D:\\Voice_AI\\app\\workers\\dubbing_tasks.py", "source_location": "L147", "receiver": "db"}, {"caller_nid": "d_voice_ai_app_workers_dubbing_tasks_run_dubbing_pipeline", "callee": "TranscriptSegment", "is_member_call": false, "indirect": true, "context": "argument", "source_file": "D:\\Voice_AI\\app\\workers\\dubbing_tasks.py", "source_location": "L147"}, {"caller_nid": "d_voice_ai_app_workers_dubbing_tasks_run_dubbing_pipeline", "callee": "asc", "is_member_call": true, "source_file": "D:\\Voice_AI\\app\\workers\\dubbing_tasks.py", "source_location": "L149", "receiver": null}, {"caller_nid": "d_voice_ai_app_workers_dubbing_tasks_run_dubbing_pipeline", "callee": "append", "is_member_call": true, "source_file": "D:\\Voice_AI\\app\\workers\\dubbing_tasks.py", "source_location": "L152", "receiver": "segments_data"}, {"caller_nid": "d_voice_ai_app_workers_dubbing_tasks_run_dubbing_pipeline", "callee": "info", "is_member_call": true, "source_file": "D:\\Voice_AI\\app\\workers\\dubbing_tasks.py", "source_location": "L159", "receiver": "logger"}, {"caller_nid": "d_voice_ai_app_workers_dubbing_tasks_run_dubbing_pipeline", "callee": "first", "is_member_call": true, "source_file": "D:\\Voice_AI\\app\\workers\\dubbing_tasks.py", "source_location": "L169", "receiver": null}, {"caller_nid": "d_voice_ai_app_workers_dubbing_tasks_run_dubbing_pipeline", "callee": "query", "is_member_call": true, "source_file": "D:\\Voice_AI\\app\\workers\\dubbing_tasks.py", "source_location": "L169", "receiver": "db"}, {"caller_nid": "d_voice_ai_app_workers_dubbing_tasks_run_dubbing_pipeline", "callee": "JobStep", "is_member_call": false, "indirect": true, "context": "argument", "source_file": "D:\\Voice_AI\\app\\workers\\dubbing_tasks.py", "source_location": "L169"}, {"caller_nid": "d_voice_ai_app_workers_dubbing_tasks_run_dubbing_pipeline", "callee": "utcnow", "is_member_call": true, "source_file": "D:\\Voice_AI\\app\\workers\\dubbing_tasks.py", "source_location": "L176", "receiver": "datetime"}, {"caller_nid": "d_voice_ai_app_workers_dubbing_tasks_run_dubbing_pipeline", "callee": "commit", "is_member_call": true, "source_file": "D:\\Voice_AI\\app\\workers\\dubbing_tasks.py", "source_location": "L178", "receiver": "db"}, {"caller_nid": "d_voice_ai_app_workers_dubbing_tasks_run_dubbing_pipeline", "callee": "check_url_safety", "is_member_call": false, "source_file": "D:\\Voice_AI\\app\\workers\\dubbing_tasks.py", "source_location": "L185", "receiver": null}, {"caller_nid": "d_voice_ai_app_workers_dubbing_tasks_run_dubbing_pipeline", "callee": "Exception", "is_member_call": false, "source_file": "D:\\Voice_AI\\app\\workers\\dubbing_tasks.py", "source_location": "L187", "receiver": null}, {"caller_nid": "d_voice_ai_app_workers_dubbing_tasks_run_dubbing_pipeline", "callee": "get_adapter_for_url", "is_member_call": false, "source_file": "D:\\Voice_AI\\app\\workers\\dubbing_tasks.py", "source_location": "L193", "receiver": null}, {"caller_nid": "d_voice_ai_app_workers_dubbing_tasks_run_dubbing_pipeline", "callee": "Exception", "is_member_call": false, "source_file": "D:\\Voice_AI\\app\\workers\\dubbing_tasks.py", "source_location": "L195", "receiver": null}, {"caller_nid": "d_voice_ai_app_workers_dubbing_tasks_run_dubbing_pipeline", "callee": "lower", "is_member_call": true, "source_file": "D:\\Voice_AI\\app\\workers\\dubbing_tasks.py", "source_location": "L196", "receiver": null}, {"caller_nid": "d_voice_ai_app_workers_dubbing_tasks_run_dubbing_pipeline", "callee": "lower", "is_member_call": true, "source_file": "D:\\Voice_AI\\app\\workers\\dubbing_tasks.py", "source_location": "L196", "receiver": null}, {"caller_nid": "d_voice_ai_app_workers_dubbing_tasks_run_dubbing_pipeline", "callee": "get_adapter_for_url", "is_member_call": false, "source_file": "D:\\Voice_AI\\app\\workers\\dubbing_tasks.py", "source_location": "L204", "receiver": null}, {"caller_nid": "d_voice_ai_app_workers_dubbing_tasks_run_dubbing_pipeline", "callee": "extract_metadata", "is_member_call": true, "source_file": "D:\\Voice_AI\\app\\workers\\dubbing_tasks.py", "source_location": "L205", "receiver": "adapter"}, {"caller_nid": "d_voice_ai_app_workers_dubbing_tasks_run_dubbing_pipeline", "callee": "get", "is_member_call": true, "source_file": "D:\\Voice_AI\\app\\workers\\dubbing_tasks.py", "source_location": "L206", "receiver": "meta"}, {"caller_nid": "d_voice_ai_app_workers_dubbing_tasks_run_dubbing_pipeline", "callee": "get", "is_member_call": true, "source_file": "D:\\Voice_AI\\app\\workers\\dubbing_tasks.py", "source_location": "L208", "receiver": "meta"}, {"caller_nid": "d_voice_ai_app_workers_dubbing_tasks_run_dubbing_pipeline", "callee": "get_adapter_for_url", "is_member_call": false, "source_file": "D:\\Voice_AI\\app\\workers\\dubbing_tasks.py", "source_location": "L215", "receiver": null}, {"caller_nid": "d_voice_ai_app_workers_dubbing_tasks_run_dubbing_pipeline", "callee": "download", "is_member_call": true, "source_file": "D:\\Voice_AI\\app\\workers\\dubbing_tasks.py", "source_location": "L216", "receiver": "adapter"}, {"caller_nid": "d_voice_ai_app_workers_dubbing_tasks_run_dubbing_pipeline", "callee": "exists", "is_member_call": true, "source_file": "D:\\Voice_AI\\app\\workers\\dubbing_tasks.py", "source_location": "L217", "receiver": null}, {"caller_nid": "d_voice_ai_app_workers_dubbing_tasks_run_dubbing_pipeline", "callee": "FileNotFoundError", "is_member_call": false, "source_file": "D:\\Voice_AI\\app\\workers\\dubbing_tasks.py", "source_location": "L218", "receiver": null}, {"caller_nid": "d_voice_ai_app_workers_dubbing_tasks_run_dubbing_pipeline", "callee": "getsize", "is_member_call": true, "source_file": "D:\\Voice_AI\\app\\workers\\dubbing_tasks.py", "source_location": "L219", "receiver": null}, {"caller_nid": "d_voice_ai_app_workers_dubbing_tasks_run_dubbing_pipeline", "callee": "exists", "is_member_call": true, "source_file": "D:\\Voice_AI\\app\\workers\\dubbing_tasks.py", "source_location": "L221", "receiver": null}, {"caller_nid": "d_voice_ai_app_workers_dubbing_tasks_run_dubbing_pipeline", "callee": "copy", "is_member_call": true, "source_file": "D:\\Voice_AI\\app\\workers\\dubbing_tasks.py", "source_location": "L222", "receiver": "shutil"}, {"caller_nid": "d_voice_ai_app_workers_dubbing_tasks_run_dubbing_pipeline", "callee": "FileNotFoundError", "is_member_call": false, "source_file": "D:\\Voice_AI\\app\\workers\\dubbing_tasks.py", "source_location": "L225", "receiver": null}, {"caller_nid": "d_voice_ai_app_workers_dubbing_tasks_run_dubbing_pipeline", "callee": "exists", "is_member_call": true, "source_file": "D:\\Voice_AI\\app\\workers\\dubbing_tasks.py", "source_location": "L229", "receiver": null}, {"caller_nid": "d_voice_ai_app_workers_dubbing_tasks_run_dubbing_pipeline", "callee": "FileNotFoundError", "is_member_call": false, "source_file": "D:\\Voice_AI\\app\\workers\\dubbing_tasks.py", "source_location": "L230", "receiver": null}, {"caller_nid": "d_voice_ai_app_workers_dubbing_tasks_run_dubbing_pipeline", "callee": "getsize", "is_member_call": true, "source_file": "D:\\Voice_AI\\app\\workers\\dubbing_tasks.py", "source_location": "L231", "receiver": null}, {"caller_nid": "d_voice_ai_app_workers_dubbing_tasks_run_dubbing_pipeline", "callee": "ValueError", "is_member_call": false, "source_file": "D:\\Voice_AI\\app\\workers\\dubbing_tasks.py", "source_location": "L233", "receiver": null}, {"caller_nid": "d_voice_ai_app_workers_dubbing_tasks_run_dubbing_pipeline", "callee": "extract_audio_from_video", "is_member_call": false, "source_file": "D:\\Voice_AI\\app\\workers\\dubbing_tasks.py", "source_location": "L239", "receiver": null}, {"caller_nid": "d_voice_ai_app_workers_dubbing_tasks_run_dubbing_pipeline", "callee": "copy", "is_member_call": true, "source_file": "D:\\Voice_AI\\app\\workers\\dubbing_tasks.py", "source_location": "L246", "receiver": "shutil"}, {"caller_nid": "d_voice_ai_app_workers_dubbing_tasks_run_dubbing_pipeline", "callee": "get_ffmpeg_path", "is_member_call": false, "source_file": "D:\\Voice_AI\\app\\workers\\dubbing_tasks.py", "source_location": "L249", "receiver": null}, {"caller_nid": "d_voice_ai_app_workers_dubbing_tasks_run_dubbing_pipeline", "callee": "run", "is_member_call": true, "source_file": "D:\\Voice_AI\\app\\workers\\dubbing_tasks.py", "source_location": "L253", "receiver": "subprocess"}, {"caller_nid": "d_voice_ai_app_workers_dubbing_tasks_run_dubbing_pipeline", "callee": "str", "is_member_call": false, "indirect": true, "context": "argument", "source_file": "D:\\Voice_AI\\app\\workers\\dubbing_tasks.py", "source_location": "L260"}, {"caller_nid": "d_voice_ai_app_workers_dubbing_tasks_run_dubbing_pipeline", "callee": "loads", "is_member_call": true, "source_file": "D:\\Voice_AI\\app\\workers\\dubbing_tasks.py", "source_location": "L261", "receiver": "json"}, {"caller_nid": "d_voice_ai_app_workers_dubbing_tasks_run_dubbing_pipeline", "callee": "get", "is_member_call": true, "source_file": "D:\\Voice_AI\\app\\workers\\dubbing_tasks.py", "source_location": "L262", "receiver": "voice_config"}, {"caller_nid": "d_voice_ai_app_workers_dubbing_tasks_run_dubbing_pipeline", "callee": "transcribe_audio", "is_member_call": false, "source_file": "D:\\Voice_AI\\app\\workers\\dubbing_tasks.py", "source_location": "L264", "receiver": null}, {"caller_nid": "d_voice_ai_app_workers_dubbing_tasks_run_dubbing_pipeline", "callee": "TranscriptSegment", "is_member_call": false, "source_file": "D:\\Voice_AI\\app\\workers\\dubbing_tasks.py", "source_location": "L268", "receiver": null}, {"caller_nid": "d_voice_ai_app_workers_dubbing_tasks_run_dubbing_pipeline", "callee": "add", "is_member_call": true, "source_file": "D:\\Voice_AI\\app\\workers\\dubbing_tasks.py", "source_location": "L278", "receiver": "db"}, {"caller_nid": "d_voice_ai_app_workers_dubbing_tasks_run_dubbing_pipeline", "callee": "str", "is_member_call": false, "indirect": true, "context": "argument", "source_file": "D:\\Voice_AI\\app\\workers\\dubbing_tasks.py", "source_location": "L295"}, {"caller_nid": "d_voice_ai_app_workers_dubbing_tasks_run_dubbing_pipeline", "callee": "loads", "is_member_call": true, "source_file": "D:\\Voice_AI\\app\\workers\\dubbing_tasks.py", "source_location": "L296", "receiver": "json"}, {"caller_nid": "d_voice_ai_app_workers_dubbing_tasks_run_dubbing_pipeline", "callee": "get", "is_member_call": true, "source_file": "D:\\Voice_AI\\app\\workers\\dubbing_tasks.py", "source_location": "L297", "receiver": "voice_config"}, {"caller_nid": "d_voice_ai_app_workers_dubbing_tasks_run_dubbing_pipeline", "callee": "translate_segments", "is_member_call": false, "source_file": "D:\\Voice_AI\\app\\workers\\dubbing_tasks.py", "source_location": "L299", "receiver": null}, {"caller_nid": "d_voice_ai_app_workers_dubbing_tasks_run_dubbing_pipeline", "callee": "order_by", "is_member_call": true, "source_file": "D:\\Voice_AI\\app\\workers\\dubbing_tasks.py", "source_location": "L302", "receiver": null}, {"caller_nid": "d_voice_ai_app_workers_dubbing_tasks_run_dubbing_pipeline", "callee": "query", "is_member_call": true, "source_file": "D:\\Voice_AI\\app\\workers\\dubbing_tasks.py", "source_location": "L302", "receiver": "db"}, {"caller_nid": "d_voice_ai_app_workers_dubbing_tasks_run_dubbing_pipeline", "callee": "TranscriptSegment", "is_member_call": false, "indirect": true, "context": "argument", "source_file": "D:\\Voice_AI\\app\\workers\\dubbing_tasks.py", "source_location": "L302"}, {"caller_nid": "d_voice_ai_app_workers_dubbing_tasks_run_dubbing_pipeline", "callee": "asc", "is_member_call": true, "source_file": "D:\\Voice_AI\\app\\workers\\dubbing_tasks.py", "source_location": "L304", "receiver": null}, {"caller_nid": "d_voice_ai_app_workers_dubbing_tasks_run_dubbing_pipeline", "callee": "get", "is_member_call": true, "source_file": "D:\\Voice_AI\\app\\workers\\dubbing_tasks.py", "source_location": "L307", "receiver": "data_seg"}, {"caller_nid": "d_voice_ai_app_workers_dubbing_tasks_run_dubbing_pipeline", "callee": "str", "is_member_call": false, "indirect": true, "context": "argument", "source_file": "D:\\Voice_AI\\app\\workers\\dubbing_tasks.py", "source_location": "L319"}, {"caller_nid": "d_voice_ai_app_workers_dubbing_tasks_run_dubbing_pipeline", "callee": "loads", "is_member_call": true, "source_file": "D:\\Voice_AI\\app\\workers\\dubbing_tasks.py", "source_location": "L320", "receiver": "json"}, {"caller_nid": "d_voice_ai_app_workers_dubbing_tasks_run_dubbing_pipeline", "callee": "get", "is_member_call": true, "source_file": "D:\\Voice_AI\\app\\workers\\dubbing_tasks.py", "source_location": "L321", "receiver": "voice_config"}, {"caller_nid": "d_voice_ai_app_workers_dubbing_tasks_run_dubbing_pipeline", "callee": "get", "is_member_call": true, "source_file": "D:\\Voice_AI\\app\\workers\\dubbing_tasks.py", "source_location": "L322", "receiver": "voice_config"}, {"caller_nid": "d_voice_ai_app_workers_dubbing_tasks_run_dubbing_pipeline", "callee": "get", "is_member_call": true, "source_file": "D:\\Voice_AI\\app\\workers\\dubbing_tasks.py", "source_location": "L323", "receiver": "voice_config"}, {"caller_nid": "d_voice_ai_app_workers_dubbing_tasks_run_dubbing_pipeline", "callee": "select_voice", "is_member_call": false, "source_file": "D:\\Voice_AI\\app\\workers\\dubbing_tasks.py", "source_location": "L329", "receiver": null}, {"caller_nid": "d_voice_ai_app_workers_dubbing_tasks_run_dubbing_pipeline", "callee": "str", "is_member_call": false, "indirect": true, "context": "argument", "source_file": "D:\\Voice_AI\\app\\workers\\dubbing_tasks.py", "source_location": "L337"}, {"caller_nid": "d_voice_ai_app_workers_dubbing_tasks_run_dubbing_pipeline", "callee": "loads", "is_member_call": true, "source_file": "D:\\Voice_AI\\app\\workers\\dubbing_tasks.py", "source_location": "L338", "receiver": "json"}, {"caller_nid": "d_voice_ai_app_workers_dubbing_tasks_run_dubbing_pipeline", "callee": "get", "is_member_call": true, "source_file": "D:\\Voice_AI\\app\\workers\\dubbing_tasks.py", "source_location": "L339", "receiver": "voice_config"}, {"caller_nid": "d_voice_ai_app_workers_dubbing_tasks_run_dubbing_pipeline", "callee": "generate_all_tts_segments", "is_member_call": false, "source_file": "D:\\Voice_AI\\app\\workers\\dubbing_tasks.py", "source_location": "L341", "receiver": null}, {"caller_nid": "d_voice_ai_app_workers_dubbing_tasks_run_dubbing_pipeline", "callee": "order_by", "is_member_call": true, "source_file": "D:\\Voice_AI\\app\\workers\\dubbing_tasks.py", "source_location": "L350", "receiver": null}, {"caller_nid": "d_voice_ai_app_workers_dubbing_tasks_run_dubbing_pipeline", "callee": "query", "is_member_call": true, "source_file": "D:\\Voice_AI\\app\\workers\\dubbing_tasks.py", "source_location": "L350", "receiver": "db"}, {"caller_nid": "d_voice_ai_app_workers_dubbing_tasks_run_dubbing_pipeline", "callee": "TranscriptSegment", "is_member_call": false, "indirect": true, "context": "argument", "source_file": "D:\\Voice_AI\\app\\workers\\dubbing_tasks.py", "source_location": "L350"}, {"caller_nid": "d_voice_ai_app_workers_dubbing_tasks_run_dubbing_pipeline", "callee": "asc", "is_member_call": true, "source_file": "D:\\Voice_AI\\app\\workers\\dubbing_tasks.py", "source_location": "L352", "receiver": null}, {"caller_nid": "d_voice_ai_app_workers_dubbing_tasks_run_dubbing_pipeline", "callee": "get", "is_member_call": true, "source_file": "D:\\Voice_AI\\app\\workers\\dubbing_tasks.py", "source_location": "L355", "receiver": "data_seg"}, {"caller_nid": "d_voice_ai_app_workers_dubbing_tasks_run_dubbing_pipeline", "callee": "generate_srt_file", "is_member_call": false, "source_file": "D:\\Voice_AI\\app\\workers\\dubbing_tasks.py", "source_location": "L370", "receiver": null}, {"caller_nid": "d_voice_ai_app_workers_dubbing_tasks_run_dubbing_pipeline", "callee": "generate_vtt_file", "is_member_call": false, "source_file": "D:\\Voice_AI\\app\\workers\\dubbing_tasks.py", "source_location": "L371", "receiver": null}, {"caller_nid": "d_voice_ai_app_workers_dubbing_tasks_run_dubbing_pipeline", "callee": "str", "is_member_call": false, "indirect": true, "context": "argument", "source_file": "D:\\Voice_AI\\app\\workers\\dubbing_tasks.py", "source_location": "L378"}, {"caller_nid": "d_voice_ai_app_workers_dubbing_tasks_run_dubbing_pipeline", "callee": "loads", "is_member_call": true, "source_file": "D:\\Voice_AI\\app\\workers\\dubbing_tasks.py", "source_location": "L379", "receiver": "json"}, {"caller_nid": "d_voice_ai_app_workers_dubbing_tasks_run_dubbing_pipeline", "callee": "get", "is_member_call": true, "source_file": "D:\\Voice_AI\\app\\workers\\dubbing_tasks.py", "source_location": "L380", "receiver": "voice_config"}, {"caller_nid": "d_voice_ai_app_workers_dubbing_tasks_run_dubbing_pipeline", "callee": "get", "is_member_call": true, "source_file": "D:\\Voice_AI\\app\\workers\\dubbing_tasks.py", "source_location": "L381", "receiver": "voice_config"}, {"caller_nid": "d_voice_ai_app_workers_dubbing_tasks_run_dubbing_pipeline", "callee": "merge_tts_with_video", "is_member_call": false, "source_file": "D:\\Voice_AI\\app\\workers\\dubbing_tasks.py", "source_location": "L386", "receiver": null}, {"caller_nid": "d_voice_ai_app_workers_dubbing_tasks_run_dubbing_pipeline", "callee": "getsize", "is_member_call": true, "source_file": "D:\\Voice_AI\\app\\workers\\dubbing_tasks.py", "source_location": "L395", "receiver": null}, {"caller_nid": "d_voice_ai_app_workers_dubbing_tasks_run_dubbing_pipeline", "callee": "exists", "is_member_call": true, "source_file": "D:\\Voice_AI\\app\\workers\\dubbing_tasks.py", "source_location": "L400", "receiver": null}, {"caller_nid": "d_voice_ai_app_workers_dubbing_tasks_run_dubbing_pipeline", "callee": "getsize", "is_member_call": true, "source_file": "D:\\Voice_AI\\app\\workers\\dubbing_tasks.py", "source_location": "L400", "receiver": null}, {"caller_nid": "d_voice_ai_app_workers_dubbing_tasks_run_dubbing_pipeline", "callee": "ValueError", "is_member_call": false, "source_file": "D:\\Voice_AI\\app\\workers\\dubbing_tasks.py", "source_location": "L401", "receiver": null}, {"caller_nid": "d_voice_ai_app_workers_dubbing_tasks_run_dubbing_pipeline", "callee": "exists", "is_member_call": true, "source_file": "D:\\Voice_AI\\app\\workers\\dubbing_tasks.py", "source_location": "L402", "receiver": null}, {"caller_nid": "d_voice_ai_app_workers_dubbing_tasks_run_dubbing_pipeline", "callee": "ValueError", "is_member_call": false, "source_file": "D:\\Voice_AI\\app\\workers\\dubbing_tasks.py", "source_location": "L403", "receiver": null}, {"caller_nid": "d_voice_ai_app_workers_dubbing_tasks_run_dubbing_pipeline", "callee": "Export", "is_member_call": false, "source_file": "D:\\Voice_AI\\app\\workers\\dubbing_tasks.py", "source_location": "L409", "receiver": null}, {"caller_nid": "d_voice_ai_app_workers_dubbing_tasks_run_dubbing_pipeline", "callee": "getsize", "is_member_call": true, "source_file": "D:\\Voice_AI\\app\\workers\\dubbing_tasks.py", "source_location": "L412", "receiver": null}, {"caller_nid": "d_voice_ai_app_workers_dubbing_tasks_run_dubbing_pipeline", "callee": "Export", "is_member_call": false, "source_file": "D:\\Voice_AI\\app\\workers\\dubbing_tasks.py", "source_location": "L414", "receiver": null}, {"caller_nid": "d_voice_ai_app_workers_dubbing_tasks_run_dubbing_pipeline", "callee": "getsize", "is_member_call": true, "source_file": "D:\\Voice_AI\\app\\workers\\dubbing_tasks.py", "source_location": "L417", "receiver": null}, {"caller_nid": "d_voice_ai_app_workers_dubbing_tasks_run_dubbing_pipeline", "callee": "Export", "is_member_call": false, "source_file": "D:\\Voice_AI\\app\\workers\\dubbing_tasks.py", "source_location": "L419", "receiver": null}, {"caller_nid": "d_voice_ai_app_workers_dubbing_tasks_run_dubbing_pipeline", "callee": "getsize", "is_member_call": true, "source_file": "D:\\Voice_AI\\app\\workers\\dubbing_tasks.py", "source_location": "L422", "receiver": null}, {"caller_nid": "d_voice_ai_app_workers_dubbing_tasks_run_dubbing_pipeline", "callee": "exists", "is_member_call": true, "source_file": "D:\\Voice_AI\\app\\workers\\dubbing_tasks.py", "source_location": "L422", "receiver": null}, {"caller_nid": "d_voice_ai_app_workers_dubbing_tasks_run_dubbing_pipeline", "callee": "add", "is_member_call": true, "source_file": "D:\\Voice_AI\\app\\workers\\dubbing_tasks.py", "source_location": "L424", "receiver": "db"}, {"caller_nid": "d_voice_ai_app_workers_dubbing_tasks_run_dubbing_pipeline", "callee": "add", "is_member_call": true, "source_file": "D:\\Voice_AI\\app\\workers\\dubbing_tasks.py", "source_location": "L425", "receiver": "db"}, {"caller_nid": "d_voice_ai_app_workers_dubbing_tasks_run_dubbing_pipeline", "callee": "add", "is_member_call": true, "source_file": "D:\\Voice_AI\\app\\workers\\dubbing_tasks.py", "source_location": "L426", "receiver": "db"}, {"caller_nid": "d_voice_ai_app_workers_dubbing_tasks_run_dubbing_pipeline", "callee": "utcnow", "is_member_call": true, "source_file": "D:\\Voice_AI\\app\\workers\\dubbing_tasks.py", "source_location": "L436", "receiver": "datetime"}, {"caller_nid": "d_voice_ai_app_workers_dubbing_tasks_run_dubbing_pipeline", "callee": "commit", "is_member_call": true, "source_file": "D:\\Voice_AI\\app\\workers\\dubbing_tasks.py", "source_location": "L437", "receiver": "db"}, {"caller_nid": "d_voice_ai_app_workers_dubbing_tasks_run_dubbing_pipeline", "callee": "error", "is_member_call": true, "source_file": "D:\\Voice_AI\\app\\workers\\dubbing_tasks.py", "source_location": "L440", "receiver": "logger"}, {"caller_nid": "d_voice_ai_app_workers_dubbing_tasks_run_dubbing_pipeline", "callee": "e", "is_member_call": false, "indirect": true, "context": "argument", "source_file": "D:\\Voice_AI\\app\\workers\\dubbing_tasks.py", "source_location": "L440"}, {"caller_nid": "d_voice_ai_app_workers_dubbing_tasks_run_dubbing_pipeline", "callee": "utcnow", "is_member_call": true, "source_file": "D:\\Voice_AI\\app\\workers\\dubbing_tasks.py", "source_location": "L443", "receiver": "datetime"}, {"caller_nid": "d_voice_ai_app_workers_dubbing_tasks_run_dubbing_pipeline", "callee": "e", "is_member_call": false, "indirect": true, "context": "argument", "source_file": "D:\\Voice_AI\\app\\workers\\dubbing_tasks.py", "source_location": "L444"}, {"caller_nid": "d_voice_ai_app_workers_dubbing_tasks_run_dubbing_pipeline", "callee": "utcnow", "is_member_call": true, "source_file": "D:\\Voice_AI\\app\\workers\\dubbing_tasks.py", "source_location": "L450", "receiver": "datetime"}, {"caller_nid": "d_voice_ai_app_workers_dubbing_tasks_run_dubbing_pipeline", "callee": "commit", "is_member_call": true, "source_file": "D:\\Voice_AI\\app\\workers\\dubbing_tasks.py", "source_location": "L451", "receiver": "db"}, {"caller_nid": "d_voice_ai_app_workers_dubbing_tasks_run_dubbing_pipeline", "callee": "info", "is_member_call": true, "source_file": "D:\\Voice_AI\\app\\workers\\dubbing_tasks.py", "source_location": "L452", "receiver": "logger"}, {"caller_nid": "d_voice_ai_app_workers_dubbing_tasks_run_dubbing_pipeline", "callee": "error", "is_member_call": true, "source_file": "D:\\Voice_AI\\app\\workers\\dubbing_tasks.py", "source_location": "L455", "receiver": "logger"}, {"caller_nid": "d_voice_ai_app_workers_dubbing_tasks_run_dubbing_pipeline", "callee": "e", "is_member_call": false, "indirect": true, "context": "argument", "source_file": "D:\\Voice_AI\\app\\workers\\dubbing_tasks.py", "source_location": "L455"}, {"caller_nid": "d_voice_ai_app_workers_dubbing_tasks_run_dubbing_pipeline", "callee": "rollback", "is_member_call": true, "source_file": "D:\\Voice_AI\\app\\workers\\dubbing_tasks.py", "source_location": "L456", "receiver": "db"}, {"caller_nid": "d_voice_ai_app_workers_dubbing_tasks_run_dubbing_pipeline", "callee": "first", "is_member_call": true, "source_file": "D:\\Voice_AI\\app\\workers\\dubbing_tasks.py", "source_location": "L457", "receiver": null}, {"caller_nid": "d_voice_ai_app_workers_dubbing_tasks_run_dubbing_pipeline", "callee": "query", "is_member_call": true, "source_file": "D:\\Voice_AI\\app\\workers\\dubbing_tasks.py", "source_location": "L457", "receiver": "db"}, {"caller_nid": "d_voice_ai_app_workers_dubbing_tasks_run_dubbing_pipeline", "callee": "DubbingJob", "is_member_call": false, "indirect": true, "context": "argument", "source_file": "D:\\Voice_AI\\app\\workers\\dubbing_tasks.py", "source_location": "L457"}, {"caller_nid": "d_voice_ai_app_workers_dubbing_tasks_run_dubbing_pipeline", "callee": "e", "is_member_call": false, "indirect": true, "context": "argument", "source_file": "D:\\Voice_AI\\app\\workers\\dubbing_tasks.py", "source_location": "L460"}, {"caller_nid": "d_voice_ai_app_workers_dubbing_tasks_run_dubbing_pipeline", "callee": "commit", "is_member_call": true, "source_file": "D:\\Voice_AI\\app\\workers\\dubbing_tasks.py", "source_location": "L461", "receiver": "db"}, {"caller_nid": "d_voice_ai_app_workers_dubbing_tasks_run_dubbing_pipeline", "callee": "close", "is_member_call": true, "source_file": "D:\\Voice_AI\\app\\workers\\dubbing_tasks.py", "source_location": "L463", "receiver": "db"}]}